pylinc/__init__.py
pylinc/core.py
pylinc/cosmo.py
pylinc/healpix.py
pylinc/matplotlib.py
pylinc-0.0.1.dist-info/LICENSE
pylinc-0.0.1.dist-info/METADATA
pylinc-0.0.1.dist-info/WHEEL
pylinc-0.0.1.dist-info/top_level.txt
pylinc-0.0.1.dist-info/RECORD
